pecli.py
Startup/__init__.py
Startup/startup.py
Startup/validation.py
cli/__init__.py
cli/arg_parse.py
cli/bar.py
cli/config.py
cli/handle_callbacks.py
cli/logger.py
parallelencodecli-0.1.3.dist-info/LICENSE.md
parallelencodecli-0.1.3.dist-info/METADATA
parallelencodecli-0.1.3.dist-info/WHEEL
parallelencodecli-0.1.3.dist-info/entry_points.txt
parallelencodecli-0.1.3.dist-info/top_level.txt
parallelencodecli-0.1.3.dist-info/RECORD
