Metadata-Version: 2.1
Name: parallelencodecli
Version: 0.1.3
Summary: Parallel encoding cli interface
Home-page: https://github.com/parallelencode/pecli
Author: Parallel Encoders
Author-email: eli.stonium@gmail.com
License: UNKNOWN
Platform: UNKNOWN
Classifier: Programming Language :: Python :: 3
Classifier: License :: OSI Approved :: GNU General Public License v3 or later (GPLv3+)
Classifier: Operating System :: OS Independent
Requires-Python: >=3.6
Requires-Dist: fuzzywuzzy
Requires-Dist: matplotlib
Requires-Dist: numpy
Requires-Dist: parallelencode
Requires-Dist: psutil
Requires-Dist: scipy
Requires-Dist: tqdm
